polemarch/__init__.py
polemarch/__main__.py
polemarch/metrics.py
polemarch/notificator.py
polemarch/settings.ini
polemarch/wapp.py
polemarch/wsgi.py
polemarch/api/__init__.py
polemarch/api/fields.py
polemarch/api/filters.py
polemarch/api/permissions.py
polemarch/api/schema.py
polemarch/api/swagger.py
polemarch/api/v4/__init__.py
polemarch/api/v4/ansible.py
polemarch/api/v4/base.py
polemarch/api/v4/execution_templates.py
polemarch/api/v4/history.py
polemarch/api/v4/hooks.py
polemarch/api/v4/hosts.py
polemarch/api/v4/oauth2_token.py
polemarch/api/v4/projects.py
polemarch/api/v4/statistics.py
polemarch/api/v4/users.py
polemarch/doc/html/.buildinfo
polemarch/doc/html/api.html
polemarch/doc/html/backup.html
polemarch/doc/html/cla.html
polemarch/doc/html/config.html
polemarch/doc/html/contribute.html
polemarch/doc/html/genindex.html
polemarch/doc/html/gui.html
polemarch/doc/html/http-routingtable.html
polemarch/doc/html/index.html
polemarch/doc/html/installation.html
polemarch/doc/html/objects.inv
polemarch/doc/html/plugins.html
polemarch/doc/html/quickstart.html
polemarch/doc/html/search.html
polemarch/doc/html/searchindex.js
polemarch/doc/html/.doctrees/api.doctree
polemarch/doc/html/.doctrees/backup.doctree
polemarch/doc/html/.doctrees/cla.doctree
polemarch/doc/html/.doctrees/config.doctree
polemarch/doc/html/.doctrees/contribute.doctree
polemarch/doc/html/.doctrees/environment.pickle
polemarch/doc/html/.doctrees/gui.doctree
polemarch/doc/html/.doctrees/index.doctree
polemarch/doc/html/.doctrees/installation.doctree
polemarch/doc/html/.doctrees/plugins.doctree
polemarch/doc/html/.doctrees/quickstart.doctree
polemarch/doc/html/_images/change_password.png
polemarch/doc/html/_images/community_template.png
polemarch/doc/html/_images/community_template_1.png
polemarch/doc/html/_images/community_template_2.png
polemarch/doc/html/_images/community_template_3.png
polemarch/doc/html/_images/community_template_4.png
polemarch/doc/html/_images/community_template_5.png
polemarch-4.0.0.dist-info/LICENSE
polemarch-4.0.0.dist-info/METADATA
polemarch-4.0.0.dist-info/WHEEL
polemarch-4.0.0.dist-info/dependency_links.txt
polemarch-4.0.0.dist-info/entry_points.txt
polemarch-4.0.0.dist-info/top_level.txt
polemarch-4.0.0.dist-info/RECORD
