Metadata-Version: 2.1
Name: polemarch
Version: 4.0.0
Summary: Polemarch is ansible based service for orchestration infrastructure.
Author-email: VST Consulting <sergey.k@vstconsulting.net>
License: AGPLv3+
Project-URL: Home, https://gitlab.com/vstconsulting/polemarch
Project-URL: Web Site, https://polemarch.org/
Project-URL: Issue Tracker, https://gitlab.com/vstconsulting/polemarch/issues
Project-URL: Source Code, https://gitlab.com/vstconsulting/polemarch
Project-URL: Releases, https://github.com/vstconsulting/polemarch/releases
Project-URL: DockerHub, https://hub.docker.com/r/vstconsulting/polemarch/
Project-URL: Documentation, https://about.polemarch.org/
Classifier: Development Status :: 5 - Production/Stable
Classifier: Environment :: Web Environment
Classifier: Framework :: Django
Classifier: Framework :: Django :: 5.1
Classifier: Operating System :: POSIX
Classifier: Programming Language :: Python
Classifier: Programming Language :: Python :: 3
Classifier: Programming Language :: Python :: 3 :: Only
Classifier: Programming Language :: Python :: 3.10
Classifier: Programming Language :: Python :: 3.11
Classifier: Programming Language :: Python :: 3.12
Classifier: Programming Language :: Python :: Implementation :: CPython
Classifier: Topic :: Internet :: WWW/HTTP
Classifier: Topic :: Internet :: WWW/HTTP :: Dynamic Content
Classifier: Topic :: Software Development :: User Interfaces
Classifier: Topic :: System :: Systems Administration
Classifier: Topic :: Utilities
Requires-Python: >=3.10
License-File: LICENSE
Requires-Dist: vstutils[ldap,prod,rpc] ~=5.12.3
Requires-Dist: markdown2 ~=2.4.10
Requires-Dist: docutils ~=0.20.0
Requires-Dist: gitpython ~=3.1.32
Requires-Dist: gitdb2 ~=4.0.2
Requires-Dist: requests ~=2.31.0
Requires-Dist: urllib3 ~=1.26.16
Provides-Extra: ansible-core
Requires-Dist: polemarch-ansible ~=3.0.1 ; extra == 'ansible-core'
Provides-Extra: ansible29
Requires-Dist: polemarch-ansible ~=2.2.0 ; extra == 'ansible29'
Provides-Extra: mysql
Requires-Dist: mysqlclient <2.2 ; extra == 'mysql'
Provides-Extra: postgresql
Requires-Dist: psycopg[c,pool] ; extra == 'postgresql'
Provides-Extra: production
Requires-Dist: uvloop ; extra == 'production'
Requires-Dist: httptools ; extra == 'production'
Provides-Extra: test
Requires-Dist: django-test-migrations ~=1.3.0 ; extra == 'test'
Requires-Dist: vstutils[ldap,prod,rpc,test] ~=5.12.3 ; extra == 'test'
